{"results": [{"gender": "female", "name": {"title": "Mrs", "first": "Isidora", "last": "Prokopenko"}, "location": {"street": {"number": 8022, "name": "Milniy provulok"}, "city": "Obuhiv", "state": "Zakarpatska", "country": "Ukraine", "postcode": 48376, "coordinates": {"latitude": "80.2084", "longitude": "31.3670"}, "timezone": {"offset": "+11:00", "description": "Magadan, Solomon Islands, New Caledonia"}}, "email": "isidora.prokopenko@example.com", "login": {"uuid": "5b5fc994-6633-4616-a638-b8bc167fac1f", "username": "orangepanda601", "password": "chrisbln", "salt": "ypmyhAiy", "md5": "73a473a11bdb495054e3298067d6ec5d", "sha1": "5d3875df309f1c7eae5500440f8028d3398870b8", "sha256": "447f99e300c264efc40397306fc378406c12d8e07a27a4f69c5dbd78db243491"}, "dob": {"date": "1986-11-16T23:12:24.258Z", "age": 38}, "registered": {"date": "2018-04-11T18:15:21.410Z", "age": 6}, "phone": "(068) M96-7194", "cell": "(098) B55-2172", "id": {"name": "", "value": null}, "picture": {"large": "https://randomuser.me/api/portraits/women/6.jpg", "medium": "https://randomuser.me/api/portraits/med/women/6.jpg", "thumbnail": "https://randomuser.me/api/portraits/thumb/women/6.jpg"}, "nat": "UA"}], "info": {"seed": "dda23b643891c1dd", "results": 1, "page": 1, "version": "1.4"}}